rblx/__init__.py
rblx/users.py
rblx/utils.py
rblx-0.1.0.dist-info/licenses/LICENSE
tests/__init__.py
tests/test_rblx.py
rblx-0.1.0.dist-info/METADATA
rblx-0.1.0.dist-info/WHEEL
rblx-0.1.0.dist-info/top_level.txt
rblx-0.1.0.dist-info/RECORD
