Metadata-Version: 2.4
Name: rblx
Version: 0.1.0
Summary: A Python library for Roblox utilities
Author: TuFueguito
Classifier: Programming Language :: Python :: 3
Classifier: License :: OSI Approved :: MIT License
Classifier: Operating System :: OS Independent
Requires-Python: >=3.8
License-File: LICENSE
Dynamic: author
Dynamic: classifier
Dynamic: license-file
Dynamic: requires-python
Dynamic: summary
